[{
	"raw": {},
	"required": [
		"Filename",
		"Size"
	],
	"package": "osmo-bsc-meas-utils",
	"source": "osmo-bsc",
	"version": "1.13.0-2build1",
	"section": "universe/net",
	"priority": "optional",
	"architecture": "amd64",
	"depends": [
		"libc6 (>= 2.34)",
		"libosmo-mgcp-client14 (>= 1.13.0)",
		"libosmo-sigtran11 (>= 2.1.0)",
		"libosmoabis15 (>= 2.0.0)",
		"libosmocore22 (>= 1.10.0)",
		"libosmoctrl0 (>= 1.10.0)",
		"libosmogsm20 (>= 1.10.0)",
		"libosmonetif11 (>= 1.5.0)",
		"libosmovty13 (>= 1.10.0)",
		"libtalloc2 (>= 2.0.4~git20101213)"
	],
	"installedSize": 1705,
	"maintainer": "Ubuntu Developers <ubuntu-devel-discuss@lists.ubuntu.com>",
	"description": "Command line utilities to manage measurement reports",
	"homepage": "https://osmocom.org/projects/osmobsc",
	"filename": "pool/universe/o/osmo-bsc/osmo-bsc-meas-utils_1.13.0-2build1_amd64.deb",
	"size": 564238,
	"md5": "6f95c015b4552061e98ee10d0d98602c",
	"sha1": "89d5984778bf2d92b738070aff4584383fd27a16",
	"sha256": "49d31225e8e3191bf7e8b3741de01e8afb6bea3d638cce137f72c23c4fb5ed9f",
	"sha512": "75351d2c2f33a463afb3393a2f2edb4229de1649a7d680d7d8b8a82bf865c45d5190a24f468f8d98f774314c0b2cc82152fd42f54bf9a436ef6665df6dbbd664",
	"descriptionMd5": "058572607ee119ca875e792b5a9fbb0d"
}]