{
	"raw": {},
	"required": [
		"Filename",
		"Size"
	],
	"package": "appdata-tools",
	"source": "appstream-glib",
	"version": "0.5.13-1",
	"section": "universe/devel",
	"priority": "optional",
	"architecture": "all",
	"depends": [
		"appstream-util"
	],
	"installedSize": 11,
	"maintainer": "Ubuntu Developers <ubuntu-devel-discuss@lists.ubuntu.com>",
	"description": "Transitional dummy package (appdata-tools -> appstream-util)",
	"homepage": "http://people.freedesktop.org/~hughsient/appstream-glib/",
	"filename": "pool/universe/a/appstream-glib/appdata-tools_0.5.13-1_all.deb",
	"size": 1780,
	"md5": "4427e95c40a7b478aae7e53faf2e2c93",
	"sha1": "a766a9888d3fa30d298793ead7d1d06db2dd2e95",
	"sha256": "3112b0dadb204bc67340e2cbf8417ca65fec0bc927336e01a192841a1f45ae62",
	"descriptionMd5": "7a2da4f6b579fb7ab97e5466f78afd42"
}