{"raw":{},"required":["Filename","Size"],"package":"kamera-dbg","source":"kamera","version":"4:15.12.3-0ubuntu1","section":"universe/debug","priority":"extra","architecture":"amd64","depends":["kamera (= 4:15.12.3-0ubuntu1)"],"replaces":["kdegraphics-dbg (<< 4:4.6.90)"],"breaks":["kdegraphics-dbg (<< 4:4.6.90)"],"installedSize":839,"maintainer":"Ubuntu Developers <ubuntu-devel-discuss@lists.ubuntu.com>","description":"debugging symbols for kamera","homepage":"https://projects.kde.org/projects/kde/kdegraphics/kamera","filename":"pool/universe/k/kamera/kamera-dbg_15.12.3-0ubuntu1_amd64.deb","size":802872,"md5":"1cb44839146a2d9af64aad222e661cc2","sha1":"ae6d4f77e18875f00020b2e9145b560d02cccf97","sha256":"78120f308375582ad28e718e51d7edc44b5f75e340e02bca077c5591706cfe53","descriptionMd5":"9e007e6f71e9ab2608720e505c605a3e"}