{
	"raw": {},
	"required": [
		"Filename",
		"Size"
	],
	"package": "refdb-www",
	"source": "refdb",
	"version": "1.0.2-3ubuntu1",
	"section": "universe/text",
	"priority": "optional",
	"architecture": "all",
	"depends": [
		"refdb-server",
		"libapache2-mod-php",
		"php-xsl"
	],
	"recommends": [
		"php-yaz"
	],
	"installedSize": 824,
	"maintainer": "Ubuntu Developers <ubuntu-devel-discuss@lists.ubuntu.com>",
	"description": "Reference database and bibliography tool - www server",
	"homepage": "http://refdb.sf.net",
	"filename": "pool/universe/r/refdb/refdb-www_1.0.2-3ubuntu1_all.deb",
	"size": 70052,
	"md5": "8232727905248932508a3e83d55d8d5d",
	"sha1": "77b17c8c9fbc285f28a047696a1b673a253cd7ed",
	"sha256": "b50650e0eb17b32cff39c8fdf5e7f613bbc83364922aebdbb0f54d00d713a337",
	"descriptionMd5": "77c7207e8f3370ae3a8002998276e379"
}