{"raw":{},"required":["Filename","Size"],"package":"agtl","version":"0.8.0.3-1ubuntu1","section":"universe/python","priority":"extra","architecture":"all","depends":["python (>= 2.5)","python-support (>= 0.90.0)","python-gtk2","python (>= 2.6) | python-simplejson"],"installedSize":1372,"maintainer":"Ubuntu Developers <ubuntu-devel-discuss@lists.ubuntu.com>","description":"Tool for paperless geocaching","homepage":"http://wiki.openmoko.org/wiki/Advanced_Geocaching_Tool_for_Linux","filename":"pool/universe/a/agtl/agtl_0.8.0.3-1ubuntu1_all.deb","size":190642,"md5":"694d989cc013a9f38d56451d0b4d19f0","sha1":"22a6f42e889aa78084c712974c2870ca5600b186","sha256":"b53cca22c959d57c2dc18e6bb4fe7794067f043d499337fceb4fc0e8a977c306","descriptionMd5":"beb821a6116ad18158f611c92a41fe20"}