[{
	"raw": {},
	"required": [
		"Filename",
		"Size"
	],
	"package": "libglobus-xio-popen-driver-dbg",
	"source": "globus-xio-popen-driver",
	"version": "2.3-3",
	"section": "universe/debug",
	"priority": "extra",
	"architecture": "amd64",
	"depends": [
		"libglobus-xio-popen-driver0 (= 2.3-3)"
	],
	"replaces": [
		"globus-xio-popen-driver-dbg (<< 2.3-3~)"
	],
	"conflicts": [
		"globus-xio-popen-driver-dbg (<< 2.3-3~)"
	],
	"installedSize": 98,
	"maintainer": "Ubuntu Developers <ubuntu-devel-discuss@lists.ubuntu.com>",
	"description": "Globus Toolkit - Globus XIO Pipe Open Driver Debug Symbols",
	"homepage": "http://www.globus.org/",
	"filename": "pool/universe/g/globus-xio-popen-driver/libglobus-xio-popen-driver-dbg_2.3-3_amd64.deb",
	"size": 17368,
	"md5": "7e40b191b078eae8dcaa79ccc83c7cdd",
	"sha1": "f7ec83007879d0bee2d854ca3aba7a76525e5650",
	"sha256": "6897c2556c920d8f4eaa104b1c09b5dfe3cc686db3b074c5f6374ec320e8fa1b",
	"descriptionMd5": "18d76173394058523affa6f98a328eba"
}]