[{
	"raw": {},
	"required": [
		"Filename",
		"Size"
	],
	"package": "python-restkit",
	"version": "4.2.2-1",
	"section": "universe/python",
	"priority": "extra",
	"architecture": "all",
	"depends": [
		"python (>= 2.7)",
		"python (<< 2.8)",
		"python:any (>= 2.7.1-0ubuntu2)",
		"python-http-parser (>= 0.8.1)",
		"python-socketpool (>= 0.5.0)"
	],
	"installedSize": 212,
	"maintainer": "Ubuntu Developers <ubuntu-devel-discuss@lists.ubuntu.com>",
	"description": "Restkit is an HTTP resource kit for Python",
	"homepage": "http://benoitc.github.com/restkit",
	"filename": "pool/universe/p/python-restkit/python-restkit_4.2.2-1_all.deb",
	"size": 40806,
	"md5": "94ba7dfed63babc249068b7a292ca454",
	"sha1": "21e2999765a0da5136b3d3e95d5e297f7f38f128",
	"sha256": "7eecb2ed50a778bd883ca30c655122a277b721a8dda67b1180d8c56b51f2d148",
	"descriptionMd5": "20b87671fd530edca8ef7d20f9ad5cd9"
}]