[{
	"raw": {},
	"required": [
		"Filename",
		"Size"
	],
	"package": "python-pyasn1-doc",
	"source": "pyasn1",
	"version": "0.4.8-1ubuntu0.2",
	"section": "doc",
	"priority": "optional",
	"architecture": "all",
	"depends": [
		"libjs-sphinxdoc (>= 4.3)"
	],
	"suggests": [
		"doc-base"
	],
	"replaces": [
		"python-pyasn1 (<< 0.4.2-1)"
	],
	"breaks": [
		"python-pyasn1 (<< 0.4.2-1)"
	],
	"installedSize": 1625,
	"maintainer": "Ubuntu Developers <ubuntu-devel-discuss@lists.ubuntu.com>",
	"description": "ASN.1 library for Python (documentation)",
	"homepage": "http://snmplabs.com/pyasn1/index.html",
	"builtUsing": "alabaster (= 0.7.12-1), sphinx (= 4.3.2-1)",
	"filename": "pool/main/p/pyasn1/python-pyasn1-doc_0.4.8-1ubuntu0.2_all.deb",
	"size": 102486,
	"md5": "9365a7fd8765f7ac27099f9afad46306",
	"sha1": "cce261e11eec8738aa553039adf5bbd92def39de",
	"sha256": "15fb4fa656832441e55203bea489eea3d0f5279edadbc0353674c695e834887c",
	"sha512": "15de98bb5343d3aaa7e8eb75534f2eea60265949a83eb7ffce00a3f935d0981a305e8b35710569683fa00e11fe901f53d9341b1e572db51c13f03594efa57bac",
	"descriptionMd5": "b26e4a6c9c40c3d351af8f894e5b9833"
},{
	"raw": {},
	"required": [
		"Filename",
		"Size"
	],
	"package": "python-pyasn1-doc",
	"source": "pyasn1",
	"version": "0.4.8-1",
	"section": "doc",
	"priority": "optional",
	"architecture": "all",
	"depends": [
		"libjs-sphinxdoc (>= 1.0)"
	],
	"suggests": [
		"doc-base"
	],
	"replaces": [
		"python-pyasn1 (<< 0.4.2-1)"
	],
	"breaks": [
		"python-pyasn1 (<< 0.4.2-1)"
	],
	"installedSize": 1470,
	"maintainer": "Ubuntu Developers <ubuntu-devel-discuss@lists.ubuntu.com>",
	"description": "ASN.1 library for Python (documentation)",
	"homepage": "http://snmplabs.com/pyasn1/index.html",
	"builtUsing": "alabaster (= 0.7.8-1.1), sphinx (= 2.4.3-4)",
	"filename": "pool/main/p/pyasn1/python-pyasn1-doc_0.4.8-1_all.deb",
	"size": 95296,
	"md5": "53b4241c2aaa8884a79a12a7c48fd650",
	"sha1": "8db663e82da5866ce07f72e07b7202eda38627d2",
	"sha256": "9581f3aa89e8480f7e4012aca5d4cfc867ae1e139febfc748e6ee4adcd5a394f",
	"sha512": "44d2a3a651cecf91d7e3fac225eadea2f22d81da580d4ad452a5dfe07dc0e51898668ae925463047aa200977aabca69c0338cb3c70f87b30781e2f861b0f2905",
	"descriptionMd5": "b26e4a6c9c40c3d351af8f894e5b9833"
}]