[{
	"raw": {},
	"required": [
		"Filename",
		"Size"
	],
	"package": "libghc-futhark-server-doc",
	"source": "haskell-futhark-server",
	"version": "1.2.3.0-1",
	"section": "universe/doc",
	"priority": "optional",
	"architecture": "all",
	"depends": [
		"haddock-interface-42"
	],
	"recommends": [
		"ghc-doc",
		"libghc-futhark-data-doc",
		"libghc-futhark-server-dev",
		"libghc-temporary-doc",
		"libjs-mathjax"
	],
	"suggests": [
		"libghc-futhark-server-prof"
	],
	"installedSize": 455,
	"maintainer": "Ubuntu Developers <ubuntu-devel-discuss@lists.ubuntu.com>",
	"description": "client implementation of the Futhark server protocol; documentation",
	"homepage": "https://hackage.haskell.org/package/futhark-server",
	"filename": "pool/universe/h/haskell-futhark-server/libghc-futhark-server-doc_1.2.3.0-1_all.deb",
	"size": 44430,
	"md5": "fba14b42ad1acb18f1ad22772026f9d0",
	"sha1": "c86be9a99e4875092ca0ab21d2d26eb953560e3f",
	"sha256": "9b6d5f653b11f667d7fbe5526af916a948132e1ef0714e942e70379c9b162cc6",
	"sha512": "1fd0051287bc457c56fb4d5b41f7e9b7f0e21c53360020b4b7fe9b249ef9e5906e37a203c37dc9cef7353770140610f10ba9e60c0a5fa677f79734316cc2e52d",
	"descriptionMd5": "0de146d3d965f1d4988459e16902174e"
}]