[{
	"raw": {},
	"required": [
		"Filename",
		"Size"
	],
	"package": "libgwengui-fox16-79t64",
	"source": "libgwenhywfar",
	"version": "5.12.0-1",
	"section": "universe/libs",
	"priority": "optional",
	"architecture": "amd64",
	"depends": [
		"libc6 (>= 2.4)",
		"libfox-1.6-0",
		"libgcc-s1 (>= 3.3.1)",
		"libgwenhywfar79t64 (>= 5.8.0)",
		"libstdc++6 (>= 5)"
	],
	"replaces": [
		"libgwengui-fox16-79"
	],
	"breaks": [
		"libgwengui-fox16-79 (<< 5.12.0-1)"
	],
	"installedSize": 187,
	"maintainer": "Ubuntu Developers <ubuntu-devel-discuss@lists.ubuntu.com>",
	"description": "Gwenhywfar GUI implementation for the FOX Toolkit",
	"homepage": "https://www.aquamaniac.de/rdm/projects/gwenhywfar",
	"filename": "pool/universe/libg/libgwenhywfar/libgwengui-fox16-79t64_5.12.0-1_amd64.deb",
	"size": 47460,
	"md5": "959d12ef3c558305b51bf87a27cd9c1d",
	"sha1": "f975c8070b030794651ca3b2f619fc83feff9efe",
	"sha256": "243be5694fc427adb3e33e2975ec9a9ef2484b6c9de889c5755aa97d1980fdeb",
	"sha512": "f7465bc58366db109f39384e4f867052e76e085a5951f73a52bd8f22a7444b84dc2024f8bb74a9153de4e94e14c4138e088960877767382e466d36ff87087601",
	"descriptionMd5": "48c462eccab803ea47392ad49c8d53a4"
}]