{
	"raw": {},
	"required": [
		"Filename",
		"Size"
	],
	"package": "language-pack-tr",
	"version": "1:24.04+20250130",
	"section": "translations",
	"priority": "optional",
	"architecture": "all",
	"depends": [
		"language-pack-tr-base (>= 1:24.04+20250130)"
	],
	"preDepends": [
		"dpkg (>= 1.16.1)"
	],
	"replaces": [
		"language-pack-gnome-tr (<< 1:24.04+20250130)",
		"language-pack-gnome-tr-base (<< 1:24.04+20250130)",
		"language-pack-kde-tr (<< 1:24.04+20250130)",
		"language-pack-kde-tr-base (<< 1:24.04+20250130)",
		"language-pack-tr (<< 1:24.04+20250130)",
		"language-pack-tr-base"
	],
	"installedSize": 9,
	"maintainer": "Language pack maintainers <language-packs@ubuntu.com>",
	"description": "translation updates for language Turkish",
	"filename": "pool/main/l/language-pack-tr/language-pack-tr_24.04+20250130_all.deb",
	"size": 1900,
	"md5": "bf0c452219103c966ef4fc12e7ce87ea",
	"sha1": "2dcdec3398221d1a15ffa1ba1ad34f24f7c75319",
	"sha256": "9767dfb3353d41aee27f7694e24264740e2bb84a39cdd9da927e5ec9f39f45fc",
	"sha512": "0ba21e512934110a70f0c910189e53b74aa610b49f0b3c263d1b8911a0b6bb033cc66807584508d7fe3ebb9dd0564981419ce86dbf286596c7222db48821b6c9",
	"descriptionMd5": "dfefbe4b5c37c26ad9200ad67f24f22f"
}