[{
	"raw": {},
	"required": [
		"Filename",
		"Size"
	],
	"package": "colord-gtk-utils",
	"source": "colord-gtk",
	"version": "0.1.26-1",
	"section": "universe/graphics",
	"priority": "optional",
	"architecture": "amd64",
	"depends": [
		"libc6 (>= 2.4)",
		"libcolord-gtk1 (>= 0.1.20)",
		"libcolord2 (>= 0.1.31)",
		"libglib2.0-0 (>= 2.28.0)",
		"libgtk-3-0 (>= 3.0.0)"
	],
	"installedSize": 45,
	"maintainer": "Christopher James Halse Rogers <raof@ubuntu.com>",
	"description": "miscellaneous GUI utilities interacting with colord",
	"homepage": "http://www.freedesktop.org/software/colord/",
	"filename": "pool/universe/c/colord-gtk/colord-gtk-utils_0.1.26-1_amd64.deb",
	"size": 12098,
	"md5": "6263d3523e95ffa4837cd5f780bbd3da",
	"sha1": "3a3f6751811fc956c441b601bf24ee575f336c10",
	"sha256": "8ea62cc341fa0f62470e32c41e7f29e4fc0adc2f223db272ac65effdb63737ec",
	"descriptionMd5": "77a638e1b28485e09964612dfd0ac3dc"
}]