[{"raw":{},"required":["Filename","Size"],"package":"libghc-ftphs-prof","source":"ftphs","version":"1.0.9.1-6build1","section":"universe/haskell","priority":"extra","architecture":"amd64","depends":["libghc-ftphs-dev (= 1.0.9.1-6build1)","libghc-missingh-prof-1.3.0.1-ff67b","libghc-base-prof-4.8.2.0-0d6d1","libghc-hslogger-prof-1.2.9-0320d","libghc-mtl-prof-2.2.1-3af90","libghc-network-prof-2.6.2.1-25f4f","libghc-parsec-prof-3.1.9-c97a6","libghc-regex-compat-prof-0.95.1-e570f"],"installedSize":837,"maintainer":"Ubuntu Developers <ubuntu-devel-discuss@lists.ubuntu.com>","description":"FTP Client and Server Library for Haskell; profiling libraries","homepage":"http://software.complete.org/ftphs","filename":"pool/universe/f/ftphs/libghc-ftphs-prof_1.0.9.1-6build1_amd64.deb","size":91538,"md5":"f8b5b6c5a802f1f65e2cda517f2c7a89","sha1":"3526fcb85fff18d519f3fc23fd23eafa565f569e","sha256":"db497108fe8778acbb5390ee46817ff1529811e0429ec2182df4564dd3a53a43","descriptionMd5":"40bc98c568e2144b7fb5a37460c92239"}]