[{
	"raw": {},
	"required": [
		"Filename",
		"Size"
	],
	"package": "libtest-spec-perl",
	"version": "0.51-1",
	"section": "universe/perl",
	"priority": "optional",
	"architecture": "all",
	"depends": [
		"perl",
		"libpackage-stash-perl (>= 0.23)",
		"libtest-deep-perl",
		"libtest-trap-perl",
		"libtie-ixhash-perl"
	],
	"installedSize": 106,
	"maintainer": "Ubuntu Developers <ubuntu-devel-discuss@lists.ubuntu.com>",
	"description": "Perl module to write tests in a declarative specification style",
	"homepage": "https://metacpan.org/release/Test-Spec",
	"filename": "pool/universe/libt/libtest-spec-perl/libtest-spec-perl_0.51-1_all.deb",
	"size": 39394,
	"md5": "44cbb311ad02f2d32259a35b8ba984ad",
	"sha1": "1364f3e22b442760e9fcb2776922765e3b724b8c",
	"sha256": "146c4f24a05a2c38d8dd9cf4d782e67aa7d12df5611662f8ea92fcb9dfd01e3a",
	"descriptionMd5": "7cc99ad2ddf28ae564393991e5ac4ea2"
}]