{
	"raw": {},
	"required": [
		"Filename",
		"Size"
	],
	"package": "libppsdocument-4.0-5",
	"source": "papers",
	"version": "48.0-1ubuntu1.25.10.3",
	"section": "libs",
	"priority": "optional",
	"architecture": "amd64",
	"depends": [
		"libarchive13t64 (>= 3.6.0)",
		"libc6 (>= 2.38)",
		"libcairo2 (>= 1.14.0)",
		"libdjvulibre21 (>= 3.5.28)",
		"libexempi8 (>= 2.5.0)",
		"libgdk-pixbuf-2.0-0 (>= 2.40)",
		"libglib2.0-0t64 (>= 2.80.0)",
		"libgtk-4-1 (>= 4.17.1)",
		"libpango-1.0-0 (>= 1.50.3)",
		"libpoppler-glib8t64 (>= 25.03.0)",
		"libtiff6 (>= 4.0.3)"
	],
	"installedSize": 587,
	"maintainer": "Ubuntu Developers <ubuntu-devel-discuss@lists.ubuntu.com>",
	"description": "Document (Comic Books, DjVu, PDF) rendering library",
	"homepage": "https://apps.gnome.org/Papers/",
	"filename": "pool/main/p/papers/libppsdocument-4.0-5_48.0-1ubuntu1.25.10.3_amd64.deb",
	"size": 158088,
	"md5": "ece1d81637c170208eaa85911c825824",
	"sha1": "53ca8ae19f01f281723dbb0e41638a20f25b596a",
	"sha256": "78408089358368bcce2465bfa06e3c9626e4abfd1856d8b26acc7557327bf5d4",
	"sha512": "4000e3ab0d14c259ce9b99762c655e070d71b7c7690d881a9d3e64a1f2b9a4d0f08b21d01418627ca86b8c2cb470bad78a8480638efdd3f5bfe758ea312dd72c",
	"descriptionMd5": "e5cef3658650e5234bec8f82a9f06dcf"
}