{"raw":{},"required":["Filename","Size"],"package":"libkiwix12t64","source":"libkiwix","version":"12.1.1-1.1build2","section":"universe/libs","priority":"optional","architecture":"amd64","depends":["libc6 (>= 2.38)","libcurl4t64 (>= 7.16.2)","libgcc-s1 (>= 3.3.1)","libicu74 (>= 74.1-1~)","libmicrohttpd12 (>= 0.9.50)","libpugixml1v5 (>= 1.14-0.1)","libstdc++6 (>= 13.1)","libxapian30 (>= 1.4.19~)","libzim8 (>= 8.2.1)","zlib1g (>= 1:1.1.4)","aria2"],"replaces":["libkiwix12"],"breaks":["libkiwix12 (<< 12.1.1-1.1build2)"],"installedSize":1428,"maintainer":"Ubuntu Developers <ubuntu-devel-discuss@lists.ubuntu.com>","description":"library of common code for Kiwix","homepage":"https://github.com/kiwix/libkiwix","filename":"pool/universe/libk/libkiwix/libkiwix12t64_12.1.1-1.1build2_amd64.deb","size":526652,"md5":"7550d5dbefdc6f4c59bae1f5b05bed87","sha1":"ec58098812b3a1ff071bec5955113a231aa85ee7","sha256":"d17f6a0f0087d7478bf7cdab622f5a51de12bd1c5a1e6e129060992978123c4e","sha512":"56e58d34289e58f90b3bf2e9a1c2a836a9b613cfcbf022fedf3483238017aec3377c18c631297b0c5b782e51842fe6eb4b331b7e7508a7db2a54ce9d2e827aa0","descriptionMd5":"7319cebf5cddfbdd7ae7c2c4e5180e1c"}