{"raw":{},"required":["Filename","Size"],"package":"psi-plus-webkit","source":"psi-plus","version":"1.4.554-5build6","section":"universe/net","priority":"optional","architecture":"amd64","depends":["libqca-qt5-2-plugins","libqt5sql5-sqlite","psi-plus-common (= 1.4.554-5build6)","libc6 (>= 2.34)","libgcc-s1 (>= 3.0)","libhunspell-1.7-0","libidn12 (>= 1.13)","libminizip1t64","libqca-qt5-2 (>= 2.0.2)","libqt5concurrent5t64 (>= 5.6.0~rc)","libqt5core5t64 (>= 5.15.1)","libqt5dbus5t64 (>= 5.14.1)","libqt5gui5t64 (>= 5.14.1) | libqt5gui5-gles (>= 5.14.1)","libqt5keychain1 (>= 0.7.0)","libqt5network5t64 (>= 5.6.0~beta)","libqt5sql5t64 (>= 5.0.2)","libqt5svg5 (>= 5.6.0~beta)","libqt5webkit5 (>= 5.212.0~alpha3)","libqt5widgets5t64 (>= 5.15.1)","libqt5x11extras5 (>= 5.6.0)","libqt5xml5t64 (>= 5.1.0)","libstdc++6 (>= 14)","libx11-6","zlib1g (>= 1:1.1.4)"],"recommends":["psi-plus-l10n","psi-plus-plugins","psi-plus-skins","psi-plus-sounds","sox"],"suggests":["libgnome-keyring0","xdg-utils"],"installedSize":12091,"maintainer":"Ubuntu Developers <ubuntu-devel-discuss@lists.ubuntu.com>","description":"Qt-based XMPP client (WebKit version)","homepage":"https://psi-plus.com/","filename":"pool/universe/p/psi-plus/psi-plus-webkit_1.4.554-5build6_amd64.deb","size":3981778,"md5":"d0cdcaea4a4c191b8789cf54a5ba6313","sha1":"c8266ed7cc829bdf2270c5d64ce6eee50153d04b","sha256":"34b502dbaf8d702a802bef78932a7404a64c5605e9af5d1ce8cf317b129628bc","sha512":"15b5a1344ccdbd56815e94d58b7a49bf32d92f64ec0c718a0cebe3460e65f209dea4340d993fce428c6a13f8669489bd747818832def0e7517ed5989154a1d08","descriptionMd5":"6cc6da628b4793a695180482c56e800e"}