{
	"raw": {},
	"required": [
		"Filename",
		"Size"
	],
	"package": "libapt-inst2.0",
	"source": "apt",
	"version": "1.2.10ubuntu1",
	"section": "libs",
	"priority": "important",
	"architecture": "amd64",
	"depends": [
		"libapt-pkg5.0 (>= 1.1~exp9)",
		"libc6 (>= 2.14)",
		"libgcc1 (>= 1:3.0)",
		"libstdc++6 (>= 5.2)"
	],
	"installedSize": 459,
	"maintainer": "Ubuntu Developers <ubuntu-devel-discuss@lists.ubuntu.com>",
	"description": "deb package format runtime library",
	"filename": "pool/main/a/apt/libapt-inst2.0_1.2.10ubuntu1_amd64.deb",
	"size": 55638,
	"md5": "2234fe9878de1ecb6e56b70dd9978cc1",
	"sha1": "4250fe619d4f240f913876d34e4ffd976074eeff",
	"sha256": "9d08ccdbf77bd7eacd11e7430b7b938a0660dc7d6b0e73465568388fcfd65d47",
	"descriptionMd5": "5df05e67cb17e91ac56a732061d88850"
}