{
	"raw": {},
	"required": [
		"Filename",
		"Size"
	],
	"package": "libpcl-ml1.12",
	"source": "pcl",
	"version": "1.12.1+dfsg-3build1",
	"section": "universe/libs",
	"priority": "optional",
	"architecture": "amd64",
	"depends": [
		"libc6 (>= 2.29)",
		"libgcc-s1 (>= 3.3.1)",
		"libpcl-common1.12 (>= 1.12.1+dfsg)",
		"libstdc++6 (>= 11)"
	],
	"installedSize": 181,
	"maintainer": "Ubuntu Developers <ubuntu-devel-discuss@lists.ubuntu.com>",
	"description": "Point Cloud Library - ml library",
	"homepage": "http://www.pointclouds.org/",
	"filename": "pool/universe/p/pcl/libpcl-ml1.12_1.12.1+dfsg-3build1_amd64.deb",
	"size": 69950,
	"md5": "93c3ead506d31e13ee6163805a34ea7c",
	"sha1": "67839bf41e91eec2f90fd65b2794f2154f3113e6",
	"sha256": "cd99652ecfb74c8a0c76642d6edd1af382adc86f3bd4ebf64bd80956bf233f93",
	"sha512": "763395582d031629c04eb2e33c185b1a17cfa0d1084ca64a28fcdb8c3b6db5fb335fbdf1fda9d607ee18ec24bb4dd6639e0bb3aea77df0c1d3b1b72e7ff69385",
	"descriptionMd5": "555d995717db7a2124ff109f381f6b9c"
}