[{"raw":{},"required":["Filename","Size"],"package":"gfortran-12-alpha-linux-gnu","source":"gcc-12-cross-ports (1ubuntu1.3)","version":"12.3.0-1ubuntu1~22.04cross1","section":"universe/devel","priority":"optional","architecture":"amd64","depends":["gcc-12-alpha-linux-gnu-base (= 12.3.0-1ubuntu1~22.04cross1)","gcc-12-alpha-linux-gnu (= 12.3.0-1ubuntu1~22.04cross1)","libgfortran-12-dev-alpha-cross (>= 12)","libc6.1-dev-alpha-cross (>= 2.13-0ubuntu6)","libc6 (>= 2.35)","libgmp10 (>= 2:6.2.1+dfsg)","libisl23 (>= 0.15)","libmpc3 (>= 1.1.0)","libmpfr6 (>= 3.1.3)","libzstd1 (>= 1.4.0)","zlib1g (>= 1:1.1.4)"],"suggests":["gfortran-12-doc","libcoarrays-dev"],"installedSize":22653,"maintainer":"Ubuntu Core developers <ubuntu-devel-discuss@lists.ubuntu.com>","description":"GNU Fortran compiler","homepage":"http://gcc.gnu.org/","builtUsing":"gcc-12 (= 12.3.0-1ubuntu1~22.04)","filename":"pool/universe/g/gcc-12-cross-ports/gfortran-12-alpha-linux-gnu_12.3.0-1ubuntu1~22.04cross1_amd64.deb","size":8501884,"md5":"f409f152932f55f0df16d709c5387a3d","sha1":"12bc039516c8385ab6c6dc4d3aa935bb843510cc","sha256":"e4d3342b28a29c3466238bc70c25e0fbdc291ff5ab983d0a6c015be304adaf7f","sha512":"95c71b2d03cd06e7c2c486f06d4bb4c800b84f076afff7513d7b52967a1984d358fdf206b9db72bcdd81ac1498f15e01acb0f5058adb80931a3c3bd2da1964af","descriptionMd5":"5dd93c5d21d0717205bc5a3b538b0ca2"},{"raw":{},"required":["Filename","Size"],"package":"gfortran-12-alpha-linux-gnu","source":"gcc-12-cross-ports (1ubuntu1)","version":"12-20220302-1ubuntu1cross1","section":"universe/devel","priority":"optional","architecture":"amd64","depends":["gcc-12-alpha-linux-gnu-base (= 12-20220302-1ubuntu1cross1)","gcc-12-alpha-linux-gnu (= 12-20220302-1ubuntu1cross1)","libgfortran-12-dev-alpha-cross (>= 12)","libc6.1-dev-alpha-cross (>= 2.13-0ubuntu6)","libc6 (>= 2.35)","libgmp10 (>= 2:6.2.1+dfsg)","libisl23 (>= 0.15)","libmpc3 (>= 1.1.0)","libmpfr6 (>= 3.1.3)","libzstd1 (>= 1.4.0)","zlib1g (>= 1:1.1.4)"],"suggests":["gfortran-12-doc","libcoarrays-dev"],"installedSize":22474,"maintainer":"Ubuntu Core developers <ubuntu-devel-discuss@lists.ubuntu.com>","description":"GNU Fortran compiler","homepage":"http://gcc.gnu.org/","builtUsing":"gcc-12 (= 12-20220302-1ubuntu1)","filename":"pool/universe/g/gcc-12-cross-ports/gfortran-12-alpha-linux-gnu_12-20220302-1ubuntu1cross1_amd64.deb","size":8409782,"md5":"b1e0b84996b487937eb4e9853fc26d5c","sha1":"227374cb736260612615e7b82f1f082d69bfad31","sha256":"c664b89b1e392cafbc36936d3aa302e3bc75fc2a80e34ea6c9be184119d1364e","sha512":"07c1de653250002abbfac98c1c808711c8c42ff1dec61d8d5be430e053ad00b8e8d365634128aa695b96e0e60a2075e3d8b8d37b0b17bfeca402a98e5a03885a","descriptionMd5":"5dd93c5d21d0717205bc5a3b538b0ca2"}]