[{
	"raw": {},
	"required": [
		"Filename",
		"Size"
	],
	"package": "libreoffice-l10n-te",
	"source": "libreoffice",
	"version": "4:25.8.7-0ubuntu0.25.10.1~bpo24.04.1",
	"section": "localization",
	"priority": "optional",
	"architecture": "all",
	"depends": [
		"locales | locales-all"
	],
	"preDepends": [
		"ucf",
		"libreoffice-common (>= 4:25.2.1~rc1-3~)"
	],
	"recommends": [
		"fonts-telu",
		"libreoffice-core (>> 4:25.8.7)"
	],
	"suggests": [
		"hunspell-dictionary-te | myspell-dictionary-te | libreoffice-spellcheck-te",
		"hyphen-te | libreoffice-hyphenation-te",
		"libreoffice-grammarcheck-te",
		"libreoffice-help-te",
		"mythes-te"
	],
	"installedSize": 2422,
	"maintainer": "Ubuntu Developers <ubuntu-devel-discuss@lists.ubuntu.com>",
	"description": "office productivity suite -- Telugu language package",
	"homepage": "http://www.libreoffice.org",
	"filename": "pool/main/libr/libreoffice/libreoffice-l10n-te_25.8.7-0ubuntu0.25.10.1~bpo24.04.1_all.deb",
	"size": 389172,
	"md5": "56d4350f6267b55ad75aca3dcc77935b",
	"sha1": "ca379b68686f3241c81b998c19e7fe175ddb7721",
	"sha256": "9d80857e31829fcca05fa39c899bddd4b99c1a518320b1793e5467558ad31ddd",
	"sha512": "51e631ec1b244ce6f5fa28d997f207c5de5dda1f508f2bff14d26d86d0029949f689d1a543462e36ae6aa528331856bc8c6140c695490ec91e6654f18f0302e0",
	"descriptionMd5": "61e424cfb84420f8dc211c66f1b3a533"
},{
	"raw": {},
	"required": [
		"Filename",
		"Size"
	],
	"package": "libreoffice-l10n-te",
	"source": "libreoffice",
	"version": "4:24.2.7-0ubuntu0.24.04.6",
	"section": "localization",
	"priority": "optional",
	"architecture": "all",
	"depends": [
		"libreoffice-common (>= 1:7.0.0~alpha~)",
		"locales | locales-all",
		"ucf"
	],
	"recommends": [
		"fonts-telu",
		"libreoffice-core (>> 4:24.2.7)"
	],
	"suggests": [
		"hunspell-dictionary-te | myspell-dictionary-te",
		"hyphen-te",
		"libreoffice-grammarcheck-te",
		"libreoffice-help-te",
		"mythes-te"
	],
	"installedSize": 2916,
	"maintainer": "Ubuntu Developers <ubuntu-devel-discuss@lists.ubuntu.com>",
	"description": "office productivity suite -- Telugu language package",
	"homepage": "http://www.libreoffice.org",
	"filename": "pool/main/libr/libreoffice/libreoffice-l10n-te_24.2.7-0ubuntu0.24.04.6_all.deb",
	"size": 400608,
	"md5": "b230200ca1de877de67ca0c58e3b93ee",
	"sha1": "d6dd28012fc58f16073709844b2ef4055e8af793",
	"sha256": "24175bf452364718b560e27697846376dcf4b46e9b1bf163bd8260eea73f87d9",
	"sha512": "8888f5e75bd193e35a18c0096348818271c7e9ddbdf8b05c56cfe7dbcdc5319080bc4e8e1352ee9b9c48d0b5814cf54f6fcbad43163d634b959c1b637589d4ee",
	"descriptionMd5": "61e424cfb84420f8dc211c66f1b3a533"
},{
	"raw": {},
	"required": [
		"Filename",
		"Size"
	],
	"package": "libreoffice-l10n-te",
	"source": "libreoffice",
	"version": "4:24.2.2-0ubuntu1",
	"section": "localization",
	"priority": "optional",
	"architecture": "all",
	"depends": [
		"libreoffice-common (>= 1:7.0.0~alpha~)",
		"locales | locales-all",
		"ucf"
	],
	"recommends": [
		"fonts-telu",
		"libreoffice-core (>> 4:24.2.2)"
	],
	"suggests": [
		"hunspell-dictionary-te | myspell-dictionary-te",
		"hyphen-te",
		"libreoffice-grammarcheck-te",
		"libreoffice-help-te",
		"mythes-te"
	],
	"installedSize": 2915,
	"maintainer": "Ubuntu Developers <ubuntu-devel-discuss@lists.ubuntu.com>",
	"description": "office productivity suite -- Telugu language package",
	"homepage": "http://www.libreoffice.org",
	"filename": "pool/main/libr/libreoffice/libreoffice-l10n-te_24.2.2-0ubuntu1_all.deb",
	"size": 402232,
	"md5": "def9cf37c18f704d51c741548128470e",
	"sha1": "ad94da71e3664684081c88398bffb93591e7bedb",
	"sha256": "624383919fcd39c3ce341e0690c27b567fa4d5e7a436a4680e3724b278943c1e",
	"sha512": "4d4a52295f6f0eac2220e08e1cf4fc68fac5f7bcbedfd2753a3e17f8c7382cf7f2a46dd9fc4f29fd846b20b5f8799ea6b579101b8d6ef44bdb7af324ecffcc61",
	"descriptionMd5": "61e424cfb84420f8dc211c66f1b3a533"
}]