{
	"raw": {},
	"required": [
		"Filename",
		"Size"
	],
	"package": "linux-hwe-5.4-cloud-tools-5.4.0-113",
	"source": "linux-hwe-5.4",
	"version": "5.4.0-113.127~18.04.1",
	"section": "devel",
	"priority": "optional",
	"architecture": "amd64",
	"depends": [
		"libc6 (>= 2.14)",
		"linux-hwe-5.4-cloud-tools-common"
	],
	"installedSize": 795,
	"maintainer": "Ubuntu Kernel Team <kernel-team@lists.ubuntu.com>",
	"description": "Linux kernel version specific cloud tools for version 5.4.0-113",
	"filename": "pool/main/l/linux-hwe-5.4/linux-hwe-5.4-cloud-tools-5.4.0-113_5.4.0-113.127~18.04.1_amd64.deb",
	"size": 63168,
	"md5": "9192af7b131ab83c1074b3cbec9f5dc2",
	"sha1": "181b945a3e6faceb95d1425879326d7011dcab4d",
	"sha256": "621233b72ce5091d6552e26a1ffc4d3aea566d5c0130899e739ec2394b560583",
	"sha512": "43ed51500f73d15461d2affa02b68dae7293171137c8756bb5c022c1b30e5319bc97963297c316afe76d2dfc46d1703e3d37a38f134f70d867a3540d897c647d",
	"descriptionMd5": "4d69b0869d98c93383e53d0d1a091fae"
}