{
	"raw": {},
	"required": [
		"Filename",
		"Size"
	],
	"package": "orpie",
	"version": "1.6.1-2.2",
	"section": "universe/math",
	"priority": "optional",
	"architecture": "amd64",
	"depends": [
		"libc6 (>= 2.42)",
		"libgsl28 (>= 2.8+dfsg)",
		"libncursesw6 (>= 6)",
		"libtinfo6 (>= 6)"
	],
	"recommends": [
		"sensible-utils"
	],
	"installedSize": 5367,
	"maintainer": "Ubuntu Developers <ubuntu-devel-discuss@lists.ubuntu.com>",
	"description": "RPN calculator for the terminal",
	"homepage": "https://github.com/pelzlpj/orpie",
	"filename": "pool/universe/o/orpie/orpie_1.6.1-2.2_amd64.deb",
	"size": 1313472,
	"md5": "0de6fde9b780cf867456aec61444d4d4",
	"sha1": "171e215a22859b57634dd0b5ff09427c892617bd",
	"sha256": "433f793a90b21b329adb6c81f46755f7aaf9d0fb9fb761556639172d700ffbd2",
	"sha512": "335552c624ef88549cfa4342caaf1400289b4d0f1d8dc772e374a8f189cb2b358521d4bbec4e97dc11bc8d9d70dd6df4fae89cd0fa70dfb62bfd1b3009a17cd5",
	"descriptionMd5": "6ad43083171d2ea1416cf6018ef3d857"
}