[{
	"raw": {},
	"required": [
		"Filename",
		"Size"
	],
	"package": "linux-modules-nvidia-535-5.15.0-1079-oracle",
	"source": "linux-restricted-modules-oracle-5.15",
	"version": "5.15.0-1079.85~20.04.1",
	"section": "restricted/kernel",
	"priority": "optional",
	"architecture": "amd64",
	"depends": [
		"debconf (>= 0.5) | debconf-2.0",
		"linux-image-5.15.0-1079-oracle | linux-image-unsigned-5.15.0-1079-oracle",
		"linux-signatures-nvidia-5.15.0-1079-oracle (= 5.15.0-1079.85~20.04.1)",
		"linux-objects-nvidia-535-5.15.0-1079-oracle (= 5.15.0-1079.85~20.04.1)",
		"nvidia-kernel-common-535 (>= 535.183.01)"
	],
	"installedSize": 29,
	"maintainer": "Canonical Kernel Team <kernel-team@lists.ubuntu.com>",
	"description": "Linux kernel nvidia modules for version 5.15.0-1079",
	"filename": "pool/restricted/l/linux-restricted-modules-oracle-5.15/linux-modules-nvidia-535-5.15.0-1079-oracle_5.15.0-1079.85~20.04.1_amd64.deb",
	"size": 7152,
	"md5": "6c25cd09b2ddbf3acedbaed4f542f7fc",
	"sha1": "388ba6f6a449dd2093b1ec7449976f557ba3f0ce",
	"sha256": "e97ad4e181d7684614fa12c4920634a96c530ef8137aa67b5ac85ddbea4f1517",
	"sha512": "91be57e8fb894d2d6757c68b0032ad0b7f7f0ac6842a83818a8dce978425a7eba49121bf6cc446aed31b8bdc98bbefa085d9b73ed0753c93dc8eecbc96dacc01",
	"descriptionMd5": "387a5a224e1a4490615f0bdb583e93d2"
}]