{
	"raw": {},
	"required": [
		"Filename",
		"Size"
	],
	"package": "jabber-muc",
	"version": "0.8-7",
	"section": "universe/net",
	"priority": "optional",
	"architecture": "amd64",
	"depends": [
		"libc6 (>= 2.14)",
		"libexpat1 (>= 2.0.1)",
		"libglib2.0-0 (>= 2.31.8)",
		"libidn11 (>= 1.13)",
		"adduser"
	],
	"recommends": [
		"jabberd2"
	],
	"installedSize": 233,
	"maintainer": "Ubuntu Developers <ubuntu-devel-discuss@lists.ubuntu.com>",
	"description": "Multi User Conference component for the Jabber IM server",
	"homepage": "https://web.archive.org/web/https://download.gna.org/mu-conference/",
	"filename": "pool/universe/j/jabber-muc/jabber-muc_0.8-7_amd64.deb",
	"size": 83192,
	"md5": "4232851baecf811c1ac3687c11b534c9",
	"sha1": "0b32df429f3e935deae59c1ac86fabdbab374ee9",
	"sha256": "035862d5d1fe994f0cda7beccf014381a7c9cc22d7a6299b487c1cfabffc7b21",
	"descriptionMd5": "8b95a284839a0c676d88153ca06e10ce"
}