{"raw":{},"required":["Filename","Size"],"package":"libnginx-mod-rtmp","source":"nginx","version":"1.17.10-0ubuntu1","section":"universe/httpd","priority":"optional","architecture":"amd64","depends":["nginx-common (= 1.17.10-0ubuntu1)","libc6 (>= 2.28)"],"installedSize":378,"maintainer":"Ubuntu Developers <ubuntu-devel-discuss@lists.ubuntu.com>","description":"RTMP support for Nginx","homepage":"http://nginx.net","filename":"pool/universe/n/nginx/libnginx-mod-rtmp_1.17.10-0ubuntu1_amd64.deb","size":124096,"md5":"a5a267a50c2fe771f4a6922db5730f38","sha1":"85666b3a0fec247a0055fb9674bf15eb29b5625c","sha256":"82c3d5ce9f3a6b88b1fa3936b9966bde6ae4c9401a0329da36cabed93f6df52c","descriptionMd5":"21c88e68945f219c2a8efff37ad9e624"}