{
	"raw": {},
	"required": [
		"Filename",
		"Size"
	],
	"package": "ruby-sigar",
	"version": "0.7.3-2build1",
	"section": "universe/ruby",
	"priority": "optional",
	"architecture": "amd64",
	"depends": [
		"libc6 (>= 2.14)",
		"libruby2.7 (>= 2.7.0-4)",
		"ruby (>= 1:2.7~0)",
		"ruby (<< 1:2.8~)"
	],
	"installedSize": 222,
	"maintainer": "Ubuntu Developers <ubuntu-devel-discuss@lists.ubuntu.com>",
	"description": "System Information Gatherer And Reporter",
	"homepage": "https://sigar.hyperic.com/",
	"filename": "pool/universe/r/ruby-sigar/ruby-sigar_0.7.3-2build1_amd64.deb",
	"size": 70440,
	"md5": "49eed65655263662ba29915ea8033658",
	"sha1": "d6aecc3f7629cbc9207f0cf4fd2daf374da29082",
	"sha256": "f7157e821b204577e7a9f74a9e48d3479a5fbd7d676571a52bccebb9258a79a1",
	"descriptionMd5": "bbabbe2f78e45efd14243d23c5b8c440"
}