{
	"raw": {},
	"required": [
		"Filename",
		"Size"
	],
	"package": "sd2odf",
	"source": "writerperfect",
	"version": "0.9.6-2build1",
	"section": "universe/utils",
	"priority": "optional",
	"architecture": "amd64",
	"depends": [
		"libc6 (>= 2.14)",
		"libgcc-s1 (>= 3.0)",
		"libodfgen-0.1-1",
		"librevenge-0.0-0",
		"libstaroffice-0.0-0",
		"libstdc++6 (>= 5.2)"
	],
	"installedSize": 83,
	"maintainer": "Ubuntu Developers <ubuntu-devel-discuss@lists.ubuntu.com>",
	"description": "StarOffice to OpenDocument converter",
	"filename": "pool/universe/w/writerperfect/sd2odf_0.9.6-2build1_amd64.deb",
	"size": 23372,
	"md5": "0c6537500b6878d481e01cf9bd1ab00d",
	"sha1": "a4ff622ae03ee76a4c6f366224b765f98559f995",
	"sha256": "8d4986ab8d611e37057563ea998ad521395c7dd3835ae62768f3225c97e7670d",
	"descriptionMd5": "1177dc4f8760aa3c74cd8c8db39ca539"
}