{"raw":{},"required":["Filename","Size"],"package":"uhubctl","version":"2.1.0-1","section":"universe/electronics","priority":"optional","architecture":"amd64","depends":["libc6 (>= 2.4)","libusb-1.0-0 (>= 2:1.0.16)"],"installedSize":51,"maintainer":"Ubuntu Developers <ubuntu-devel-discuss@lists.ubuntu.com>","description":"USB hub per-port power control","homepage":"https://github.com/mvp/uhubctl","filename":"pool/universe/u/uhubctl/uhubctl_2.1.0-1_amd64.deb","size":18364,"md5":"f5ddd5c4402d97772328d36422e08f68","sha1":"a20bd7e3150a0d379b7b5791efb02ce607382b86","sha256":"0ba6af60d258ea8c46b29a05acb612ac0a4f3c4f2a5264a7a4b06763bf9c36f4","descriptionMd5":"4fbea6f9fd276cb0b567e63a5ec63ffe"}