[{
	"raw": {},
	"required": [
		"Filename",
		"Size"
	],
	"package": "linux-modules-nvidia-570-6.8.0-1047-oracle",
	"source": "linux-restricted-modules-oracle-6.8",
	"version": "6.8.0-1047.48~22.04.1",
	"section": "restricted/kernel",
	"priority": "optional",
	"architecture": "amd64",
	"depends": [
		"debconf (>= 0.5) | debconf-2.0",
		"linux-image-6.8.0-1047-oracle | linux-image-unsigned-6.8.0-1047-oracle",
		"linux-signatures-nvidia-6.8.0-1047-oracle (= 6.8.0-1047.48~22.04.1)",
		"linux-objects-nvidia-570-6.8.0-1047-oracle (= 6.8.0-1047.48~22.04.1)",
		"nvidia-kernel-common-570 (>= 570.211.01)"
	],
	"installedSize": 28,
	"maintainer": "Canonical Kernel Team <kernel-team@lists.ubuntu.com>",
	"description": "Linux kernel nvidia modules for version 6.8.0-1047",
	"filename": "pool/restricted/l/linux-restricted-modules-oracle-6.8/linux-modules-nvidia-570-6.8.0-1047-oracle_6.8.0-1047.48~22.04.1_amd64.deb",
	"size": 7042,
	"md5": "597e308c48b9f104951c9c792d33160f",
	"sha1": "a255af62dce3972dab50462c7c2123be59ee726c",
	"sha256": "cbc9910557f8dd561b17f62cf908b802c51720d190dd0ff6f09e2329acd23a53",
	"sha512": "9e11a26958c19d1984e1e9e7c0e996e38025e1c45915debfb55120d538b6821ed026f58318a7a57fbe34149bf6f5f8b1c07822930d36372ca5b297dc16ecc1f9",
	"descriptionMd5": "4dfb7771d5a17e35ff0857524ab4fb03"
}]