{"raw":{},"required":["Filename","Size"],"package":"libnvidia-compute-470","source":"nvidia-graphics-drivers-470","version":"470.239.06-0ubuntu0.22.04.1","section":"restricted/libs","priority":"optional","architecture":"amd64","depends":["libc6 (>= 2.7)"],"replaces":["libcuda-10.0-1","libcuda-10.1-1","libcuda-10.2-1","libcuda-11.0-1","libcuda-11.1-1","libcuda-11.2-1","libcuda-5.0-1","libcuda-5.5-1","libcuda-6.0-1","libcuda-6.5-1","libcuda-7.0-1","libcuda-7.5-1","libcuda-8.0-1","libcuda-9.0-1","libcuda-9.1-1","libcuda-9.2-1","libnvidia-compute","libnvidia-compute-470 (<< 390.25-0ubuntu2~)","nvidia-opencl-icd"],"conflicts":["libcuda-10.0-1","libcuda-10.1-1","libcuda-10.2-1","libcuda-11.0-1","libcuda-11.1-1","libcuda-11.2-1","libcuda-5.0-1","libcuda-5.5-1","libcuda-6.0-1","libcuda-6.5-1","libcuda-7.0-1","libcuda-7.5-1","libcuda-8.0-1","libcuda-9.0-1","libcuda-9.1-1","libcuda-9.2-1","libnvidia-compute","nvidia-opencl-icd"],"installedSize":132352,"maintainer":"Ubuntu Core Developers <ubuntu-devel-discuss@lists.ubuntu.com>","description":"NVIDIA libcompute package","homepage":"http://www.nvidia.com","filename":"pool/restricted/n/nvidia-graphics-drivers-470/libnvidia-compute-470_470.239.06-0ubuntu0.22.04.1_amd64.deb","size":34694898,"md5":"90b1a6fefd5132bf0779a0fcddb05226","sha1":"7684095b4119db52ebafd13f8ab3b9a1bf7971eb","sha256":"03c69a4f31e3a8fc239f30e28ae3607180545586401b6e601438ea14ad0b3576","sha512":"5c6a84856a249cd451df82c3077aa9bd3e92cd79c7b8e8ea38b98ced40955517a79f590aa20f242de4fe6a6a3523304175d114942e3e6d62ee440621572eb526","descriptionMd5":"c7c5b2d5b16b7e02eed65de795271363"}