{"raw":{},"required":["Filename","Size"],"package":"node-request","version":"2.88.1-6","section":"universe/web","priority":"extra","architecture":"all","depends":["node-aws-sign2","node-aws4","node-caseless","node-combined-stream (>= 1.0.6~)","node-extend (>= 3.0.2~)","node-forever-agent (>= 0.6.1~)","node-form-data (>= 2.3.2~)","node-har-validator","node-http-signature","node-is-typedarray","node-isstream","node-json-stringify-safe (>= 5.0.1~)","node-mime-types (>= 2.1.19~)","node-oauth-sign (>= 0.9~)","node-performance-now","node-qs (>= 6.5.2~)","node-safe-buffer","node-tough-cookie","node-tunnel-agent (>= 0.6~)","node-uuid"],"installedSize":103,"maintainer":"Ubuntu Developers <ubuntu-devel-discuss@lists.ubuntu.com>","description":"simplified HTTP request client module for Node.js","homepage":"https://github.com/mikeal/request","filename":"pool/universe/n/node-request/node-request_2.88.1-6_all.deb","size":24884,"md5":"977d55279c993a75d86c978ec3a5377d","sha1":"d78b1c7299d259f0ad1d78e0b0bf8f1262c64099","sha256":"5b201844cfa348f4312df71949a89aa20ad8812f66ed7c66022881f404bb01a5","sha512":"2a7d6d2956fec9b7b7220d53e98a16779980f79f9cdf815e7b05c74efea2c41a840008f66650d95370a6dff99608b5bbd8002474bc531e5fbe58ab373f119d14","descriptionMd5":"e217f5776b8a0b89334521e12db8577d"}