{
	"raw": {},
	"required": [
		"Filename",
		"Size"
	],
	"package": "libreoffice-l10n-ru",
	"source": "libreoffice",
	"version": "4:25.8.5-0ubuntu0.25.10.1~bpo24.04.1",
	"section": "localization",
	"priority": "optional",
	"architecture": "all",
	"depends": [
		"locales | locales-all"
	],
	"preDepends": [
		"ucf",
		"libreoffice-common (>= 4:25.2.1~rc1-3~)"
	],
	"recommends": [
		"libreoffice-core (>> 4:25.8.5)"
	],
	"suggests": [
		"hunspell-dictionary-ru | myspell-dictionary-ru | libreoffice-spellcheck-ru",
		"hyphen-ru | libreoffice-hyphenation-ru",
		"libreoffice-grammarcheck-ru",
		"libreoffice-help-ru",
		"mythes-ru"
	],
	"installedSize": 5035,
	"maintainer": "Ubuntu Developers <ubuntu-devel-discuss@lists.ubuntu.com>",
	"description": "office productivity suite -- Russian language package",
	"homepage": "http://www.libreoffice.org",
	"filename": "pool/main/libr/libreoffice/libreoffice-l10n-ru_25.8.5-0ubuntu0.25.10.1~bpo24.04.1_all.deb",
	"size": 970100,
	"md5": "454e719810a3a7269e89124312fe58b4",
	"sha1": "7bf6402f5842f92d4186786325f5c6038617d1d6",
	"sha256": "7d9dce69ddbc5b7bd00f94da60cdf59dce3b1654cea0793e8aa65ad758a646c5",
	"sha512": "a48ac7052359e8fa26c9940f335b1ab282b735271e79a93067ab497919192c91fd60b05ce64c6a999e36de3fac9cd24ef41623ccdd2de2176aa46187bcfbe86b",
	"descriptionMd5": "58787e12e170fc436c645c007bfdc3a3"
}