{"raw":{},"required":["Filename","Size"],"package":"language-pack-gnome-ga-base","version":"1:20.04+20220818","section":"translations","priority":"optional","architecture":"all","depends":["locales (>= 2.3.6)","language-pack-gnome-ga (>= 1:20.04+20220818)"],"preDepends":["dpkg (>= 1.16.1)"],"replaces":["language-pack-ga (<< 1:20.04+20220818)","language-pack-ga-base (<< 1:20.04+20220818)","language-pack-gnome-ga (<< 1:20.04+20220818)","language-pack-gnome-ga-base (<< 1:20.04+20220818)","language-pack-kde-ga (<< 1:20.04+20220818)","language-pack-kde-ga-base (<< 1:20.04+20220818)"],"conflicts":["language-pack-gnome-ga (<< 1:20.04+20220818)"],"installedSize":1137,"maintainer":"Language pack maintainers <language-packs@ubuntu.com>","description":"GNOME translations for language Irish","filename":"pool/main/l/language-pack-gnome-ga-base/language-pack-gnome-ga-base_20.04+20220818_all.deb","size":280860,"md5":"d272faf89935ee7b64797c230b4c232c","sha1":"1cbc5d3be4bcdb258400c15934b785ce10019554","sha256":"ede7ad1b520b0c296178121554041b497cdeea5ddb3a60f5243d4d0ae7de50e0","sha512":"7392e17834cf3efc8a2c04d310ae93ae4ca2ad488831af5eb79bfac2da66e6112de5fe12defad3b01301056a3043ab27c8f21884be7eae8dfad317ec1f47b420","descriptionMd5":"4b0fc4db3cca34a82e094aa0594f30aa"}