{
	"raw": {},
	"required": [
		"Filename",
		"Size"
	],
	"package": "librte-pmd-enic17.11",
	"source": "dpdk",
	"version": "17.11.10-0ubuntu0.2",
	"section": "libs",
	"priority": "optional",
	"architecture": "amd64",
	"depends": [
		"libc6 (>= 2.14)",
		"librte-bus-pci17.11 (>= 17.11)",
		"librte-eal17.11 (>= 16.04)",
		"librte-ethdev17.11 (>= 17.11)",
		"librte-hash17.11 (>= 16.04)",
		"librte-kvargs17.11 (>= 16.04)",
		"librte-mempool17.11 (>= 16.07~rc1)"
	],
	"conflicts": [
		"libdpdk0"
	],
	"installedSize": 154,
	"maintainer": "Ubuntu Developers <ubuntu-devel-discuss@lists.ubuntu.com>",
	"description": "Data Plane Development Kit (librte-pmd-enic runtime library)",
	"homepage": "https://dpdk.org/doc/guides/nics/enic.html",
	"filename": "pool/main/d/dpdk/librte-pmd-enic17.11_17.11.10-0ubuntu0.2_amd64.deb",
	"size": 47608,
	"md5": "797907fd2063900cbfc113707c138fbf",
	"sha1": "77f6e9343a47cf6595e96993fed0653aba7012c7",
	"sha256": "8f5b4acefabb61c6ebdd5fa0680ce63fd0e54cfea394b9bf1c59f38fdeb07f78",
	"sha512": "7c2a2eec190c40dbb0feaaf5fe0568a85409b550a431aba208f832eeb14ddbcaa64d06507689549fe2bc7d368c8231a0dd7c180a60890cc776041d31a090ff31",
	"descriptionMd5": "753eb9bd7f24159b24072271b0520288"
}