{"raw":{},"required":["Filename","Size"],"package":"language-pack-gnome-id-base","version":"1:14.04+20160720","section":"translations","priority":"optional","architecture":"all","depends":["locales (>= 2.3.6)","language-pack-gnome-id (>= 1:14.04+20160720)"],"preDepends":["dpkg (>= 1.16.1)"],"replaces":["language-pack-gnome-id (<< 1:14.04+20160720)","language-pack-gnome-id-base (<< 1:14.04+20160720)","language-pack-id (<< 1:14.04+20160720)","language-pack-id-base (<< 1:14.04+20160720)","language-pack-kde-id (<< 1:14.04+20160720)","language-pack-kde-id-base (<< 1:14.04+20160720)"],"conflicts":["language-pack-gnome-id (<< 1:14.04+20160720)"],"installedSize":5712,"maintainer":"Language pack maintainers <language-packs@ubuntu.com>","description":"GNOME translations for language Indonesian","filename":"pool/main/l/language-pack-gnome-id-base/language-pack-gnome-id-base_14.04+20160720_all.deb","size":1292228,"md5":"b3960da98791e83595a7ba93e170781f","sha1":"22b4a5a1c97d85e82261bd9c91650b95b0e00ec5","sha256":"4783d04412e9dfdfe3272c21ba6a22b05e70e38862d0cc22ea47456d06aa47cb","sha512":"83987761094d84714d9d73853e58422bba0bb9be3343e6e1f5e3f7279bd8ced39637b49430edd8fe3b8bc57bdfb4fb384ad4d42951e4264665e8fc5ed085748c","descriptionMd5":"7debbdf0cb01fd3c61b80db33a66a598"}