{
	"raw": {},
	"required": [
		"Filename",
		"Size"
	],
	"package": "libghc-hxt-charproperties-prof",
	"source": "haskell-hxt-charproperties",
	"version": "9.2.0.1-6build1",
	"section": "universe/haskell",
	"priority": "extra",
	"architecture": "amd64",
	"depends": [
		"libghc-hxt-charproperties-dev (= 9.2.0.1-6build1)",
		"libghc-base-prof-4.9.1.0-d28d6"
	],
	"installedSize": 8674,
	"maintainer": "Ubuntu Developers <ubuntu-devel-discuss@lists.ubuntu.com>",
	"description": "Character properties and classes for XML and Unicode; profiling libraries",
	"homepage": "https://github.com/UweSchmidt/hxt",
	"filename": "pool/universe/h/haskell-hxt-charproperties/libghc-hxt-charproperties-prof_9.2.0.1-6build1_amd64.deb",
	"size": 646892,
	"md5": "dcc3952141e5911de89f2b12138b5e24",
	"sha1": "fa985a1bb4c5b5617d32bd5aac31302b599b10a3",
	"sha256": "e10848a5647e8fef0af58fdc56317d03beb8298ff6a5f3938f95f24ba6ecfca8",
	"descriptionMd5": "5f113ab4c1a06ffb1f1d1ee7552ea3bd"
}