{
	"raw": {},
	"required": [
		"Filename",
		"Size"
	],
	"package": "libotbapplicationengine-6.4-1",
	"source": "otb",
	"version": "6.4.0+dfsg-1",
	"section": "universe/libs",
	"priority": "optional",
	"architecture": "amd64",
	"depends": [
		"libc6 (>= 2.14)",
		"libgcc1 (>= 1:3.0)",
		"libgdal20 (>= 1.8.0)",
		"libinsighttoolkit4.12 (>= 4.12.0-dfsg1-2~)",
		"libotbcommon-6.4-1 (>= 6.4.0)",
		"libotbextendedfilename-6.4-1 (>= 6.0.0)",
		"libotbimagebase-6.4-1 (>= 6.2.0)",
		"libotbimageio-6.4-1 (>= 5.2.0)",
		"libotbiogdal-6.4-1 (>= 5.2.0)",
		"libotbmetadata-6.4-1 (>= 5.2.0)",
		"libotbossimadapters-6.4-1 (>= 5.8.0)",
		"libotbstreaming-6.4-1 (>= 5.2.1)",
		"libotbtransform-6.4-1 (>= 5.2.0)",
		"libotbvectordatabase-6.4-1 (>= 5.2.0)",
		"libotbvectordataio-6.4-1 (>= 5.2.0)",
		"libstdc++6 (>= 5.2)",
		"libtinyxml2.6.2v5"
	],
	"installedSize": 12936,
	"maintainer": "Ubuntu Developers <ubuntu-devel-discuss@lists.ubuntu.com>",
	"description": "ORFEO Toolbox library - OTBApplicationEngine",
	"homepage": "http://www.orfeo-toolbox.org/",
	"filename": "pool/universe/o/otb/libotbapplicationengine-6.4-1_6.4.0+dfsg-1_amd64.deb",
	"size": 1430484,
	"md5": "6390130f5c1087f09fddd853cb887af0",
	"sha1": "3da13584665eea2817438dfabb95fae790a9b6d5",
	"sha256": "577dcb7fdcfb7f667b23179b3e759ee0fb39dc49aac47d623becdbccc070d8d1",
	"descriptionMd5": "0f0f741ceab4e2199ddce185dae9fb30"
}