{
	"raw": {},
	"required": [
		"Filename",
		"Size"
	],
	"package": "libvarnishapi1",
	"source": "varnish",
	"version": "5.2.1-1",
	"section": "universe/libs",
	"priority": "optional",
	"architecture": "amd64",
	"depends": [
		"libc6 (>= 2.25)",
		"libpcre3"
	],
	"conflicts": [
		"libvarnish1"
	],
	"installedSize": 228,
	"maintainer": "Ubuntu Developers <ubuntu-devel-discuss@lists.ubuntu.com>",
	"description": "shared libraries for Varnish",
	"homepage": "https://www.varnish-cache.org/",
	"filename": "pool/universe/v/varnish/libvarnishapi1_5.2.1-1_amd64.deb",
	"size": 64140,
	"md5": "cab0067ba5b07979d2b4c2b2dab613d1",
	"sha1": "9350e0e353d2de1e7b51f3f02668a3252ba1d3f3",
	"sha256": "8896031379eab9b64e3bd9065613df654c076d875818693bffe4a1f8f3942dd3",
	"descriptionMd5": "b62e58460782f2fccf788b20917cd377"
}