{
	"raw": {},
	"required": [
		"Filename",
		"Size"
	],
	"package": "gerbv",
	"version": "2.10.0-2",
	"section": "universe/electronics",
	"priority": "optional",
	"architecture": "amd64",
	"depends": [
		"dconf-gsettings-backend | gsettings-backend",
		"libc6 (>= 2.38)",
		"libcairo2 (>= 1.4.10)",
		"libgdk-pixbuf-2.0-0 (>= 2.22.0)",
		"libglib2.0-0t64 (>= 2.76.0)",
		"libgtk2.0-0t64 (>= 2.24.0)"
	],
	"recommends": [
		"extra-xdg-menus"
	],
	"installedSize": 13183,
	"maintainer": "Ubuntu Developers <ubuntu-devel-discuss@lists.ubuntu.com>",
	"description": "Gerber file viewer (only RS 274 X format)",
	"homepage": "https://github.com/gerbv/gerbv",
	"filename": "pool/universe/g/gerbv/gerbv_2.10.0-2_amd64.deb",
	"size": 1828960,
	"md5": "cba2b2e97f08d17cbe4fd059a4225c77",
	"sha1": "10735d200bdce10f64377afc0957bf00886b4135",
	"sha256": "d2b3245ed8ae0e1f20790785b27e61b8961a58c3b9c5f9fd2d934adabb34ba0b",
	"sha512": "7d4611558809bb6fbc705c8f58b8fc5229c61c5aae24aa92483f781b36016eb9317cd82445681564cf69e7c9013e1ee461275b7d5791e0dace203d9d12486f0b",
	"descriptionMd5": "707f6027417af4968d51640a43048142"
}