[{
	"raw": {},
	"required": [
		"Filename",
		"Size"
	],
	"package": "linux-modules-nvidia-390-4.15.0-161-generic",
	"source": "linux-restricted-modules",
	"version": "4.15.0-161.169",
	"section": "restricted/kernel",
	"priority": "optional",
	"architecture": "amd64",
	"depends": [
		"debconf (>= 0.5) | debconf-2.0",
		"linux-image-4.15.0-161-generic | linux-image-unsigned-4.15.0-161-generic",
		"linux-signatures-nvidia-4.15.0-161-generic (= 4.15.0-161.169)",
		"linux-objects-nvidia-390-4.15.0-161-generic (= 4.15.0-161.169)",
		"nvidia-kernel-common-390 (<= 390.144-1)",
		"nvidia-kernel-common-390 (>= 390.144)"
	],
	"installedSize": 30,
	"maintainer": "Canonical Kernel Team <kernel-team@lists.ubuntu.com>",
	"description": "Linux kernel nvidia modules for version 4.15.0-161",
	"filename": "pool/restricted/l/linux-restricted-modules/linux-modules-nvidia-390-4.15.0-161-generic_4.15.0-161.169_amd64.deb",
	"size": 7028,
	"md5": "7cc8b4d30f8f1a3c216d1f49ea942575",
	"sha1": "ca003b07b379a446d663f017292b419f14ab715d",
	"sha256": "5513efcbe1c7161bb9cfc4b421f779f01ed9b408b383c34cde362192d4e131b9",
	"sha512": "f6a33b36ca9f46b2caaddc4543d8a3bc2daa01d0ebb30cbe31ea8abb59a1d2f5fea06fb3f9940e45b9ac4d5abfd1fcd047e8d6463052fe3e0e596a01ddab425e",
	"descriptionMd5": "c6eeba6c0d9e2db5bed489de85b9b272"
}]