{
	"raw": {},
	"required": [
		"Filename",
		"Size"
	],
	"package": "linux-modules-nvidia-470-5.4.0-1084-oracle",
	"source": "linux-restricted-modules-oracle",
	"version": "5.4.0-1084.92+1",
	"section": "restricted/kernel",
	"priority": "optional",
	"architecture": "amd64",
	"depends": [
		"debconf (>= 0.5) | debconf-2.0",
		"linux-image-5.4.0-1084-oracle | linux-image-unsigned-5.4.0-1084-oracle",
		"linux-signatures-nvidia-5.4.0-1084-oracle (= 5.4.0-1084.92+1)",
		"linux-objects-nvidia-470-5.4.0-1084-oracle (= 5.4.0-1084.92+1)",
		"nvidia-kernel-common-470 (<= 470.141.03-1)",
		"nvidia-kernel-common-470 (>= 470.141.03)"
	],
	"installedSize": 31,
	"maintainer": "Canonical Kernel Team <kernel-team@lists.ubuntu.com>",
	"description": "Linux kernel nvidia modules for version 5.4.0-1084",
	"filename": "pool/restricted/l/linux-restricted-modules-oracle/linux-modules-nvidia-470-5.4.0-1084-oracle_5.4.0-1084.92+1_amd64.deb",
	"size": 7032,
	"md5": "09d82d92fe5293e7bc83c8902aa41517",
	"sha1": "630bdd85d5fcc66261d7e3066e1ebae9ea262cc3",
	"sha256": "b6b79cca1f3ee64e928a48692e5b1302a45b8043ef0ac1296388768e7c5d49e4",
	"sha512": "ed8e26d533114bf648d2fe29d5445dfbe0f298d9b783bb1470dca129b60c0f8051a0598c87ee478948ff33ced6c4f5cee50b2d0a6ac9b397392783fdcdfb1c7e",
	"descriptionMd5": "be2685d167f8a592ad5a5b2514184fb4"
}