{
	"raw": {},
	"required": [
		"Filename",
		"Size"
	],
	"package": "fonts-manchufont",
	"version": "2.007.svn0068-5",
	"section": "fonts",
	"priority": "optional",
	"architecture": "all",
	"replaces": [
		"ttf-manchufont (<< 2.007.svn0068-2)"
	],
	"breaks": [
		"ttf-manchufont (<< 2.007.svn0068-2)"
	],
	"installedSize": 1428,
	"maintainer": "Ubuntu Developers <ubuntu-devel-discuss@lists.ubuntu.com>",
	"description": "Smart OpenType font for Manchu script",
	"homepage": "https://sourceforge.net/projects/manchufont/",
	"filename": "pool/main/f/fonts-manchufont/fonts-manchufont_2.007.svn0068-5_all.deb",
	"size": 1135758,
	"md5": "59b0cad64aa93a2bee50bee166d17771",
	"sha1": "d0b8175c3949c78c213f3c6066bed353c75e1eaf",
	"sha256": "7bdbb51f92d07ee8810db57433d90e932ddefb248e906568336109f29722c02b",
	"descriptionMd5": "43422cd839d1ea2881b54d015a36b75d"
}