{
	"raw": {},
	"required": [
		"Filename",
		"Size"
	],
	"package": "ibus-table-cangjie-big",
	"source": "ibus-table-chinese",
	"version": "1.8.2-3",
	"section": "utils",
	"priority": "optional",
	"architecture": "all",
	"depends": [
		"ibus-table (>= 1.9.1-1~)"
	],
	"installedSize": 1544,
	"maintainer": "Ubuntu Developers <ubuntu-devel-discuss@lists.ubuntu.com>",
	"description": "ibus-table input method: CangJie (big)",
	"homepage": "https://github.com/definite/ibus-table-chinese",
	"filename": "pool/main/i/ibus-table-chinese/ibus-table-cangjie-big_1.8.2-3_all.deb",
	"size": 416352,
	"md5": "48eacb1d4478742a388d74d0933a4a48",
	"sha1": "1d320c6552646e0dc3d5abb37a93f7850badb6b7",
	"sha256": "16c15967c88adec47be52288bebef0dda0d059b3f957e6fc04e0bc5c76e87abc",
	"descriptionMd5": "8fedd8c480d9cbf548915bcb43772119"
}