{
	"raw": {},
	"required": [
		"Filename",
		"Size"
	],
	"package": "linux-image-unsigned-6.8.0-1022-gke",
	"source": "linux-gke",
	"version": "6.8.0-1022.26",
	"section": "kernel",
	"priority": "optional",
	"architecture": "amd64",
	"depends": [
		"kmod",
		"linux-base (>= 4.5ubuntu1~16.04.1)",
		"linux-modules-6.8.0-1022-gke"
	],
	"recommends": [
		"grub-pc | grub-efi-amd64 | grub-efi-ia32 | grub | lilo"
	],
	"suggests": [
		"fdutils",
		"linux-gke-doc-6.8.0 | linux-gke-source-6.8.0",
		"linux-gke-tools",
		"linux-headers-6.8.0-1022-gke",
		"initramfs-tools | linux-initramfs-tool"
	],
	"conflicts": [
		"linux-image-6.8.0-1022-gke"
	],
	"installedSize": 15085,
	"maintainer": "Ubuntu Kernel Team <kernel-team@lists.ubuntu.com>",
	"description": "Linux kernel image for version 6.8.0 on 64 bit x86 SMP",
	"filename": "pool/main/l/linux-gke/linux-image-unsigned-6.8.0-1022-gke_6.8.0-1022.26_amd64.deb",
	"size": 15462592,
	"md5": "731eb9ee0234eced443b44fa950bcb79",
	"sha1": "98693631ecf82217c46dcd971c9f610b7f4099db",
	"sha256": "54db800d600c5dfb51dd71bbe9733119eb202f73302c3660597a7f2d3abeaaea",
	"sha512": "9a1f02e67f16d055e9c0b72dc3acc5a27800769ca382d2a8df31037c4e6c3f279f7aea82c86a202a3a8549ebb92e0bfd542cfbc57fa97b45d10c2c0f4e1a6122",
	"descriptionMd5": "c75a2ab1b9049e189ca54a06438413e2"
}