[{"raw":{},"required":["Filename","Size"],"package":"commit-patch","version":"2.6-2","section":"universe/vcs","priority":"optional","architecture":"all","depends":["perl:any","libipc-run-perl","patch","patchutils","emacsen-common (>= 2.0.8)"],"suggests":["darcs | git | mercurial | bzr | monotone | subversion | cvs"],"installedSize":82,"maintainer":"Ubuntu Developers <ubuntu-devel-discuss@lists.ubuntu.com>","description":"utility to commit fine grained patches to source code control repositories","homepage":"http://porkrind.org/commit-patch/","filename":"pool/universe/c/commit-patch/commit-patch_2.6-2_all.deb","size":18804,"md5":"06735f308d98663216409a29b9a9ecd3","sha1":"43865824cdb925efe57619022fa1d13c63fd1011","sha256":"36287cbc3d8d21406361ba645c93286d8b432b5fd16cef155cdc69e1881cf8d6","descriptionMd5":"d9329af36e0955d29b0ddb9c6275ba79"}]