[{"raw":{},"required":["Filename","Size"],"package":"php-phpmyadmin-shapefile","source":"phpmyadmin-shapefile","version":"2.1-3","section":"universe/php","priority":"optional","architecture":"all","depends":["php-common"],"suggests":["php-dbase"],"installedSize":64,"maintainer":"Ubuntu Developers <ubuntu-devel-discuss@lists.ubuntu.com>","description":"translation API for PHP using Gettext MO files","homepage":"https://github.com/phpmyadmin/shapefile","filename":"pool/universe/p/phpmyadmin-shapefile/php-phpmyadmin-shapefile_2.1-3_all.deb","size":10564,"md5":"283db41bc6749a496f2dc0d27ca1b126","sha1":"0bf2a831db3f9df32f240e5cfa52714dbcc2b7cd","sha256":"917e4a32d776cf15adbab94158a0273f16c6b6dd61fd6513942c1eba8bc4f791","descriptionMd5":"35d4387db443724ddfdfea78de6a7d3a"}]