[{
	"raw": {},
	"required": [
		"Filename",
		"Size"
	],
	"package": "xmlsysd",
	"source": "wulfware",
	"version": "2.6.0-0ubuntu5",
	"section": "universe/utils",
	"priority": "optional",
	"architecture": "amd64",
	"depends": [
		"libc6 (>= 2.15)",
		"libxml2 (>= 2.7.4)",
		"xinetd | inet-superserver",
		"update-inetd"
	],
	"installedSize": 82,
	"maintainer": "Ubuntu MOTU Developers <ubuntu-motu@lists.ubuntu.com>",
	"description": "wulfware daemon to extract data from cluster nodes",
	"homepage": "http://www.phy.duke.edu/~rgb/Beowulf/wulfware.php",
	"filename": "pool/universe/w/wulfware/xmlsysd_2.6.0-0ubuntu5_amd64.deb",
	"size": 29704,
	"md5": "1a43d1e0840ac71a3ec5080097e26484",
	"sha1": "4357e3b6d669a9e3931e792b171ecd880c887279",
	"sha256": "c293e2d75ebe0a0d1343e5f1aeb280c30e26c8c849d282e811405eb1c173e507",
	"descriptionMd5": "b8f093f1a1f9f0d9f65db03ccf2981ca"
}]